{
  "products": [
    {
      "image": "https://images.gotoliquorstore.com/product/1000003534/25aa0c40-4b12-458a-a4cf-c9d9dca08947_360_m.jpg",
      "title": "19 Crimes Cabernet Sauvignon 2017",
      "category": "RedWine",
      "quantity": 350,
      "price": 10.49
    },
    {
      "image": "https://images.gotoliquorstore.com/product/1000004042/e8a6a2b9-fd50-43b0-bce4-30475b0a3c29_360_m.jpg",
      "title": "Rombauer Chardonnay 2019",
      "category": "WhiteWine",
      "quantity": 750,
      "price": 41.99
    },
    {
      "image": "https://images.gotoliquorstore.com/product/1000008830/b39955b0-511f-434d-991d-55f20d3f674b_360_m.jpg",
      "title": "Mumm Napa Brut Rose",
      "category": "SparklingWine",
      "quantity": 350,
      "price": 22.99
    },
    {
      "image": "https://images.gotoliquorstore.com/product/1000008253/ff24958b-5452-4e7d-b8bb-d7efcf077bb1_360_m.jpg",
      "title": "Veuve Clicquot Yellow Label Brut",
      "category": "Champagne",
      "quantity": 750,
      "price": 54.99
    },
    {
      "image": "https://images.gotoliquorstore.com/product/1000027271/573c7416-c5ee-4518-9342-be182ace4831_360_m.jpg",
      "title": "Chateau d'Esclans Whispering Angel Rose",
      "category": "RoseBlushWine",
      "quantity": 350,
      "price": 21.99
    },
    {
      "image": "https://images.gotoliquorstore.com/product/1000003986/20c18002-d274-4e3c-a490-367ad76d60c8_360_m.jpg",
      "title": "Meiomi Pinot Noir",
      "category": "RedWine",
      "quantity": 750,
      "price": 21.99
    },
    {
      "image": "https://images.gotoliquorstore.com/product/1000003534/25aa0c40-4b12-458a-a4cf-c9d9dca08947_360_m.jpg",
      "title": "Lillet Blanc",
      "category": "DessertFortifiedWine",
      "quantity": 350,
      "price": 18.99
    },
    {
      "image": "https://images.gotoliquorstore.com/product/1000003611/e91a773c-a4b1-400e-b254-1ee609a16002_360_m.jpg",
      "title": "Barefoot Moscato",
      "category": "WhiteWine",
      "quantity": 750,
      "price": 6.99
    },
    {
      "image": "https://images.gotoliquorstore.com/product/1000003780/7c99b18d-49a9-49d0-ad32-8b43a71c9d9c_360_m.jpg",
      "title": "Yellow Tail Merlot 2017",
      "category": "RedWine",
      "quantity": 350,
      "price": 7.99
    },
    {
      "image": "https://images.gotoliquorstore.com/product/1000004838/5070d425-90a1-439c-b390-d7c3a9203698_360_m.jpg",
      "title": "MartiniRossi Asti",
      "category": "SparklingWine",
      "quantity": 750,
      "price": 12.99
    },
    {
      "image": "https://images.gotoliquorstore.com/product/1000006628/1ce47f72-1870-4b95-86b8-65263e46c691_360_m.jpg",
      "title": "G.H. Mumm Cordon Rouge Brut",
      "category": "Champagne",
      "quantity": 350,
      "price": 43.99
    },
    {
      "image": "https://images.gotoliquorstore.com/product/1000004053/8eb9ba03-31f7-470c-82af-9bc318cc8e8f_360_m.jpg",
      "title": "Santa Margherita Pinot Grigio 2016",
      "category": "WhiteWine",
      "quantity": 750,
      "price": 22.98
    },
    {
      "image": "https://images.gotoliquorstore.com/product/1000003554/98f1441d-cd23-43e9-b291-bcfc4fa42a46_360_m.jpg",
      "title": "Alamos Malbec 2015",
      "category": "RedWine",
      "quantity": 350,
      "price": 11.99
    },
    {
      "image": "https://images.gotoliquorstore.com/product/1000003923/8812c4a5-61f6-4a8c-b8f1-4a8ed29e9c1d_360_m.jpg",
      "title": "Kim Crawford Sauvignon Blanc",
      "category": "WhiteWine",
      "quantity": 750,
      "price": 15.99
    },
    {
      "image": "https://images.gotoliquorstore.com/product/1000005710/45b1c5b8-2e55-4443-b218-945c59f51f71_360_m.jpg",
      "title": "Barefoot Sangria",
      "category": "FruitWine",
      "quantity": 350,
      "price": 6.99
    },
    {
      "image": "https://images.gotoliquorstore.com/product/1000011328/440f9144-c044-459e-802c-64cf64692876_360_m.jpg",
      "title": "Lila Rose",
      "category": "RoseBlushWine",
      "quantity": 750,
      "price": 8.49
    },
    {
      "image": "https://images.gotoliquorstore.com/product/1000003558/1dc489fc-53a9-4161-ae06-a1da0b6a7994_360_m.jpg",
      "title": "Andre Brut",
      "category": "SparklingWine",
      "quantity": 350,
      "price": 7.99
    },
    {
      "image": "https://images.gotoliquorstore.com/product/1000003895/a111884a-460e-478e-8ac0-9b3d81c46129_360_m.jpg",
      "title": "Gekkeikan Traditional Sake",
      "category": "SakeWine",
      "quantity": 750,
      "price": 7.99
    },
    {
      "image": "https://images.gotoliquorstore.com/product/1000003699/f03ae1b4-307e-45ea-9e70-843ff5048f06_360_m.jpg",
      "title": "Chateau Ste. Michelle Riesling 2018",
      "category": "WhiteWine",
      "quantity": 350,
      "price": 11.99
    },
    {
      "image": "https://images.gotoliquorstore.com/product/1000003796/db5c7eb8-ab16-4ae5-b151-7e1c2bcf787e_360_m.jpg",
      "title": "Yellow Tail Shiraz 2017",
      "category": "RedWine",
      "quantity": 750,
      "price": 7.49
    },
    {
      "image": "https://images.gotoliquorstore.com/product/1000003977/7bcc6ccf-62d8-484b-b999-55b4919c1081_360_m.jpg",
      "title": "MartiniRossi Rosso",
      "category": "RedWine",
      "quantity": 350,
      "price": 7.49
    },
    {
      "image": "https://images.gotoliquorstore.com/product/1000005400/8ce4ce0e-b77d-4cad-b8ac-2f721451ec88_360_m.jpg",
      "title": "Franzia Crisp White",
      "category": "WhiteWine",
      "quantity": 750,
      "price": 18.49
    },
    {
      "image": "https://images.gotoliquorstore.com/product/1000003661/e1e34224-3dda-4ca1-bd87-e97d7bb62105_360_m.jpg",
      "title": "Bogle Old Vine Zinfandel 2016",
      "category": "RedWine",
      "quantity": 350,
      "price": 9.99
    },
    {
      "image": "https://images.gotoliquorstore.com/product/1000003999/fbb8891e-d9cd-4774-a284-cf25374477a1_360_m.jpg",
      "title": "MoetChandon Imperial Brut",
      "category": "Champagne",
      "quantity": 750,
      "price": 47.49
    },
    {
      "image": "https://images.gotoliquorstore.com/product/1000008217/32436306-d0ae-43f7-9b0f-8611680642e7_360_m.jpg",
      "title": "Ariel Cabernet Sauvignon 2018",
      "category": "RedWine",
      "quantity": 350,
      "price": 9.49
    },
    {
      "image": "https://images.gotoliquorstore.com/product/1000003537/f1347333-2263-4ad6-8f5f-24e9cb26a52d_360_m.jpg",
      "title": "19 Crimes Red Blend 2016",
      "category": "RedWine",
      "quantity": 750,
      "price": 10.49
    },
    {
      "image": "https://images.gotoliquorstore.com/product/1000006593/1182b2db-7e04-4a59-a1ce-eea41a2bf85f_360_m.jpg",
      "title": "JaM Cellars Butter Chardonnay 2019",
      "category": "WhiteWine",
      "quantity": 350,
      "price": 15.99
    },
    {
      "image": "https://images.gotoliquorstore.com/product/1000003614/4a55bb42-b64a-427a-9827-5046d314fc43_360_m.jpg",
      "title": "Barefoot Pink Moscato",
      "category": "RoseBlushWine",
      "quantity": 750,
      "price": 6.99
    },
    {
      "image": "https://images.gotoliquorstore.com/product/1000004937/9d99f9a8-9338-4719-9e7b-c4fa513ada91_360_m.jpg",
      "title": "Carlo Rossi Sangria",
      "category": "FruitWine",
      "quantity": 350,
      "price": 16.39
    },
    {
      "image": "https://images.gotoliquorstore.com/product/1000006159/5511cf75-3f08-4356-b3b6-07e711428ee9_360_m.jpg",
      "title": "Harveys Bristol Cream Sherry",
      "category": "FruitWine",
      "quantity": 750,
      "price": 14.99
    },
    {
      "image": "https://images.gotoliquorstore.com/product/1000003662/6efa1d99-cc48-470d-ac87-703d30901365_360_m.jpg",
      "title": "Bogle Petite Sirah 2013",
      "category": "RedWine",
      "quantity": 350,
      "price": 9.99
    },
    {
      "image": "https://images.gotoliquorstore.com/product/1000003722/39a631ab-1d64-4372-a543-1467e29b7de6_360_m.jpg",
      "title": "Cupcake Moscato 2016",
      "category": "WhiteWine",
      "quantity": 750,
      "price": 8.09
    },
    {
      "image": "https://images.gotoliquorstore.com/product/1000003747/aa8b7966-0c5e-4b48-973e-e8d2da1218de_360_m.jpg",
      "title": "Robert Mondavi Private Selection Cabernet",
      "category": "RedWine",
      "quantity": 350,
      "price": 9.99
    },
    {
      "image": "https://images.gotoliquorstore.com/product/1000003860/2c16aab6-308d-4f51-89da-4a9b6280a7b1_360_m.jpg",
      "title": "Ecco Domani Pinot Grigio",
      "category": "WhiteWine",
      "quantity": 750,
      "price": 12.99
    },
    {
      "image": "https://images.gotoliquorstore.com/product/1000005658/dd6a19fb-a5fb-4a8f-bade-539d14fe4bfb_360_m.jpg",
      "title": "Mumm Napa Brut Prestige",
      "category": "SparklingWine",
      "quantity": 350,
      "price": 24.49
    },
    {
      "image": "https://images.gotoliquorstore.com/product/1000026387/43f660e2-c1d0-4806-9fd9-9070dd6edcf8_360_m.jpg",
      "title": "Laurent-Perrier Cuvee Rose",
      "category": "Champagne",
      "quantity": 750,
      "price": 71.49
    },
    {
      "image": "https://images.gotoliquorstore.com/product/1000003701/e472b8dd-3665-4913-aa3b-0369e0e442e6_360_m.jpg",
      "title": "Chloe Rose 2017",
      "category": "RoseBlushWine",
      "quantity": 350,
      "price": 12.49
    },
    {
      "image": "https://images.gotoliquorstore.com/product/1000003863/239576d3-55d9-4488-a763-641676782ad2_360_m.jpg",
      "title": "Erath Pinot Noir 2016",
      "category": "RedWine",
      "quantity": 750,
      "price": 19.99
    },
    {
      "image": "https://images.gotoliquorstore.com/product/1000011473/7b532744-1b13-4f11-a655-011f74b0e855_360_m.jpg",
      "title": "Stella Rosa Golden Honey Peach",
      "category": "WhiteWine",
      "quantity": 750,
      "price": 12.99
    },
    {
      "image": "https://images.gotoliquorstore.com/product/1000005770/12a17f76-084d-42bc-b290-14d1942e6279_360_m.jpg",
      "title": "La Crema Monterey Chardonnay 2017",
      "category": "WhiteWine",
      "quantity": 350,
      "price": 15.99
    },
    {
      "image": "https://images.gotoliquorstore.com/product/1000003608/171a1d18-04c5-4468-b6b4-bdb6816d9d5e_360_m.jpg",
      "title": "Barefoot Merlot",
      "category": "RedWine",
      "quantity": 750,
      "price": 6.99
    },
    {
      "image": "https://images.gotoliquorstore.com/product/1000003924/7c637223-157d-4567-a8d5-c41bf7bb0ca7_360_m.jpg",
      "title": "Korbel Brut",
      "category": "SparklingWine",
      "quantity": 350,
      "price": 13.99
    },
    {
      "image": "https://images.gotoliquorstore.com/product/1000004057/2f0a8f28-f90f-4979-bb87-c1474a3f85a7_360_m.jpg",
      "title": "19 Crimes Cabernet Sauvignon 2017",
      "category": "WhiteWine",
      "quantity": 750,
      "price": 9.99
    },
    {
      "image": "https://images.gotoliquorstore.com/product/1000006195/bcd602a4-9fb4-4a2f-a9a3-4341253aa465_360_m.jpg",
      "title": "Veuve Clicquot Rose",
      "category": "Champagne",
      "quantity": 350,
      "price": 68.99
    },
    {
      "image": "https://images.gotoliquorstore.com/product/1000009655/77a90bfd-d2ea-4d65-bedc-387ccc51d8bc_360_m.jpg",
      "title": "Terrazas de los Andes Reserva Malbec 2016",
      "category": "RedWine",
      "quantity": 750,
      "price": 14.99
    },
    {
      "image": "https://images.gotoliquorstore.com/product/1000004078/bef63762-8d05-46dc-a921-3f95dd62bd03_360_m.jpg",
      "title": "Stella Rosa Platinum",
      "category": "WhiteWine",
      "quantity": 350,
      "price": 12.99
    },
    {
      "image": "https://images.gotoliquorstore.com/product/1000004936/c0b172d8-8ad5-42a7-a8f4-03d17ee66e63_360_m.jpg",
      "title": "Carlo Rossi Moscato Sangria",
      "category": "FruitWine",
      "quantity": 750,
      "price": 16.39
    },
    {
      "image": "https://images.gotoliquorstore.com/product/1000022367/58778449-0e9a-4b74-8189-4289f616db62_360_m.jpg",
      "title": "Hampton Water Rose 2020",
      "category": "RoseBlushWine",
      "quantity": 350,
      "price": 20.99
    },
    {
      "image": "https://images.gotoliquorstore.com/product/1000010047/b51843d2-0a8a-498f-9c8e-c4f16fd641f6_360_m.jpg",
      "title": "Barefoot Bubbly Extra Dry",
      "category": "SparklingWine",
      "quantity": 750,
      "price": 10.99
    },
    {
      "image": "https://images.gotoliquorstore.com/product/1000004934/56a607ed-8a8c-481c-a6ec-ff6f39c5fb8a_360_m.jpg",
      "title": "Boone's Farm Strawberry Hill",
      "category": "FruitWine",
      "quantity": 350,
      "price": 4.49
    }
  ]
}